df_api/__init__.py
df_api/apps.py
df_api/openapi.py
df_api/serializers.py
df_api/settings.py
df_api/urls.py
django_df_api-0.0.3.dist-info/METADATA
django_df_api-0.0.3.dist-info/WHEEL
django_df_api-0.0.3.dist-info/top_level.txt
django_df_api-0.0.3.dist-info/RECORD
