Metadata-Version: 2.1
Name: django-df-api
Version: 0.0.3
Summary: django-df-api
Home-page: https://apexive.com/
Author: Apexive OSS
Author-email: open-source@apexive.com
License: MIT
Classifier: Environment :: Web Environment
Classifier: Framework :: Django
Classifier: Framework :: Django :: 3.2
Classifier: Framework :: Django :: 4.0
Classifier: Intended Audience :: Developers
Classifier: License :: OSI Approved :: MIT License
Classifier: Operating System :: OS Independent
Classifier: Programming Language :: Python
Classifier: Programming Language :: Python :: 3
Classifier: Programming Language :: Python :: 3 :: Only
Classifier: Programming Language :: Python :: 3.8
Classifier: Programming Language :: Python :: 3.9
Classifier: Topic :: Internet
Requires-Python: >=3.8
Requires-Dist: django
Requires-Dist: django-rest-framework
Requires-Dist: drf-spectacular[sidecar]
